lightrag/__init__.py
lightrag_project-0.1.0.dist-info/LICENSE.md
lightrag_project-0.1.0.dist-info/METADATA
lightrag_project-0.1.0.dist-info/WHEEL
lightrag_project-0.1.0.dist-info/RECORD
